{
   "items":[{
    "title":"Interview with: Hana Biadgilgn",
    "url" :"https://www.youtube.com/watch?v=DxdZUAkFvm4",
    "image":"https://www.evangadi.com/files/misc/thumbs/hanna-thumb.jpg"
    
   },
   {
    "title":" Interview with: Fikir Tilahun",
    "url" :"https://www.youtube.com/watch?v=8I_4yJ9iDkU",
    "image":"https://www.evangadi.com/files/misc/thumbs/fikir-thumb.jpg"
   },{
    "title":" Interview with: Dereje Demissie",
    "url" :"https://www.youtube.com/watch?v=88XuaYJoP2c",
    "image":"https://www.evangadi.com/files/misc/thumbs/dereje-thumb.jpg"
   },
   {
    "title":" Interview with: Saron Tadele",
    "url" :"https://www.youtube.com/watch?v=nCwGDE3zWXg",
    "image":"https://www.evangadi.com/files/misc/thumbs/saron-thumb.jpg"
   },
   {
    "title":" Interview with: Girum Yigezu",
    "url" :"https://www.youtube.com/watch?v=jC_lf-jvdNo",
    "image":"https://www.evangadi.com/files/misc/thumbs/girum-thumb.jpg"
   },
   {
    "title":" Discussion with: Feb 2021 batch students",
    "url" :"https://www.youtube.com/watch?v=m-p0O4r9520",
    "image":"https://www.evangadi.com/files/misc/thumbs/EvangadiNight-Thumb2.jpg"
   }

    ]
}